shubha_OTT_Platform/__init__.py
shubha_OTT_Platform/implementation of OTT principles.py
shubha_OTT_Platform-0.1.dist-info/License.txt
shubha_OTT_Platform-0.1.dist-info/METADATA
shubha_OTT_Platform-0.1.dist-info/WHEEL
shubha_OTT_Platform-0.1.dist-info/top_level.txt
shubha_OTT_Platform-0.1.dist-info/RECORD
