Metadata-Version: 2.1
Name: shubha-OTT-Platform
Version: 0.1
Summary: API package that provides us the method to fetch the data from the API, along with the method to convert that into proper dataframe
Author: shubha
Author-email: shubha2001shub@email.com
License: MIT
License-File: License.txt
Requires-Dist: pandas
Requires-Dist: requests
